hipopayflake/__init__.py
hipopayflake-1.1.8.dist-info/METADATA
hipopayflake-1.1.8.dist-info/WHEEL
hipopayflake-1.1.8.dist-info/top_level.txt
hipopayflake-1.1.8.dist-info/RECORD
