Metadata-Version: 2.1
Name: hipopayflake
Version: 1.1.8
Summary: Distributed system ID generator based on snowflake.
Home-page: https://hipopay.com
Author: Qingxu Kuang
Author-email: asahikuang@gmail.com
License: UNKNOWN
Platform: UNKNOWN
Classifier: Programming Language :: Python :: 3.8
Requires-Python: >=3.8
